odoo/addons/website_anchor_smooth_scroll/README.rst
odoo/addons/website_anchor_smooth_scroll/__init__.py
odoo/addons/website_anchor_smooth_scroll/__manifest__.py
odoo/addons/website_anchor_smooth_scroll/demo/pages.xml
odoo/addons/website_anchor_smooth_scroll/i18n/bg.po
odoo/addons/website_anchor_smooth_scroll/i18n/ca.po
odoo/addons/website_anchor_smooth_scroll/i18n/de.po
odoo/addons/website_anchor_smooth_scroll/i18n/es.po
odoo/addons/website_anchor_smooth_scroll/i18n/fr.po
odoo/addons/website_anchor_smooth_scroll/i18n/it.po
odoo/addons/website_anchor_smooth_scroll/i18n/pt_BR.po
odoo/addons/website_anchor_smooth_scroll/i18n/sl.po
odoo/addons/website_anchor_smooth_scroll/i18n/website_anchor_smooth_scroll.pot
odoo/addons/website_anchor_smooth_scroll/readme/CONTRIBUTORS.rst
odoo/addons/website_anchor_smooth_scroll/readme/DESCRIPTION.rst
odoo/addons/website_anchor_smooth_scroll/readme/INSTALL.rst
odoo/addons/website_anchor_smooth_scroll/readme/ROADMAP.rst
odoo/addons/website_anchor_smooth_scroll/readme/USAGE.rst
odoo/addons/website_anchor_smooth_scroll/static/description/icon.png
odoo/addons/website_anchor_smooth_scroll/static/description/index.html
odoo/addons/website_anchor_smooth_scroll/static/src/js/website_anchor_smooth_scroll.js
odoo/addons/website_anchor_smooth_scroll/views/assets.xml
odoo12_addon_website_anchor_smooth_scroll-12.0.1.0.0.99.dev16.dist-info/METADATA
odoo12_addon_website_anchor_smooth_scroll-12.0.1.0.0.99.dev16.dist-info/WHEEL
odoo12_addon_website_anchor_smooth_scroll-12.0.1.0.0.99.dev16.dist-info/top_level.txt
odoo12_addon_website_anchor_smooth_scroll-12.0.1.0.0.99.dev16.dist-info/RECORD
