Metadata-Version: 2.1
Name: odoo12-addon-website-anchor-smooth-scroll
Version: 12.0.1.0.0.99.dev16
Summary: Replace default behavior for internal links (anchor only) with smooth scroll
Home-page: https://github.com/OCA/website
Author: Tecnativa, LasLabs, Nicolas JEUDY, Odoo Community Association (OCA)
Author-email: support@odoo-community.org
License: AGPL-3
Platform: UNKNOWN
Classifier: Programming Language :: Python
Classifier: Framework :: Odoo
Classifier: Framework :: Odoo :: 12.0
Classifier: License :: OSI Approved :: GNU Affero General Public License v3
Requires-Python: >=3.5
Requires-Dist: odoo <12.1dev,>=12.0a
